{
    "User": {
        "id":{
            "int": {"min": 1, "max": 100}
        },
        "firstname": {
            "string": [
              "Abel",
              "Betsegaw",
              "Bisrat",
              "MElkamu",
              "Yidne"
             ]
        },
        "lastname": {
            "string": [
              "Zeleke",
              "Abebe",
              "Jenbere",
              "Abraraw",
              "Bantrga"
            ]
        },
        "age": {
            "int": { "min":20, "max": 26}
        },
        "Gender": {
            "string": [
                "M"
                ]
        },
        "height": {
            "string": [
              "180cm",
              "170cm",
              "160cm",
              "177cm",
              "169cm"
              ]
        }
    }
}
